django_auditmatic/__init__.py
django_auditmatic/admin.py
django_auditmatic/apps.py
django_auditmatic/models.py
django_auditmatic/permission.py
django_auditmatic/util.py
django_auditmatic/views.py
django_auditmatic/configuration/__init__.py
django_auditmatic/configuration/data_classes.py
django_auditmatic/configuration/utils.py
django_auditmatic/install/__init__.py
django_auditmatic/install/audit.py
django_auditmatic/install/audit_permission.py
django_auditmatic/management/__init__.py
django_auditmatic/management/commands/__init__.py
django_auditmatic/management/commands/install_audit.py
django_auditmatic/management/commands/install_audit_permission.py
django_auditmatic/migrations/__init__.py
django_auditmatic/tests/__init__.py
django_auditmatic/tests/test_configuration.py
django_auditmatic/tests/features/__init__.py
django_auditmatic/tests/features/steps/__init__.py
django_auditmatic/tests/features/steps/given.py
django_auditmatic/tests/features/steps/then.py
django_auditmatic/tests/features/steps/when.py
django_auditmatic/tests/test_audit_permission/__init__.py
django_auditmatic/tests/test_generate/__init__.py
django_auditmatic/tests/test_generate/test_function.py
django_auditmatic/tests/test_generate/test_table.py
django_auditmatic/tests/test_generate/test_trigger.py
django_auditmatic/utils/__init__.py
django_auditmatic/utils/generate/__init__.py
django_auditmatic/utils/generate/extension.py
django_auditmatic/utils/generate/function.py
django_auditmatic/utils/generate/table.py
django_auditmatic/utils/generate/trigger.py
django_model_auditmatic/__init__.py
django_model_auditmatic/asgi.py
django_model_auditmatic/settings.py
django_model_auditmatic/urls.py
django_model_auditmatic/wsgi.py
django_model_auditmatic-0.2.0.dist-info/LICENSE
django_model_auditmatic-0.2.0.dist-info/METADATA
django_model_auditmatic-0.2.0.dist-info/WHEEL
django_model_auditmatic-0.2.0.dist-info/top_level.txt
django_model_auditmatic-0.2.0.dist-info/RECORD
