Metadata-Version: 2.1
Name: django-model-auditmatic
Version: 0.2.0
Summary: Audit support for Django models using PostgreSQL triggers and stored procedures.
Home-page: https://github.com/BillSchumacher/django-model-auditmatic
Author: Bill Schumacher
Author-email: william.schumacher@gmail.com
License: MIT
Classifier: License :: OSI Approved :: MIT License
Classifier: Framework :: Django
Classifier: Framework :: Django :: 4.0
Classifier: Programming Language :: Python
Classifier: Programming Language :: Python :: 3.10
Classifier: Programming Language :: Python :: 3.9
Classifier: Programming Language :: Python :: 3.8
Classifier: Topic :: Database
Classifier: Topic :: Software Development :: Libraries
License-File: LICENSE
Requires-Dist: django
Requires-Dist: psycopg2
